Metadata-Version: 2.1
Name: sphinxcontrib-gtagjs
Version: 0.2.1
Summary: Sphinx extension to render global site tag of Google.
Home-page: https://github.com/attakei/sphinxcontrib-gtagjs
Author: attakei
Author-email: attakei@gmail.com
License: UNKNOWN
Platform: UNKNOWN
Classifier: Development Status :: 3 - Alpha
Classifier: Framework :: Sphinx
Classifier: Framework :: Sphinx :: Extension
Classifier: Intended Audience :: Developers
Classifier: License :: OSI Approved :: MIT License
Classifier: Programming Language :: Python :: 3.6
Classifier: Programming Language :: Python :: 3.7
Classifier: Programming Language :: Python :: 3.8
Classifier: Programming Language :: Python :: 3.9
Classifier: Programming Language :: Python :: 3.10
Classifier: Topic :: Documentation :: Sphinx
Provides-Extra: packaging
Provides-Extra: linting
